MANIFEST.in
README.rst
TITLE.txt
lh-agpl3-LICENSE.txt
setup.py
bin/bx822-qmail-remote.py
bin/dsnMsgPlugin.py
bin/fbxoMarmeSetup.sh
bin/inMailDsnPlugin.py
bin/inMailDsnProc.py
bin/inMailNotmuch.py
bin/inMailRetrieve.py
bin/marmeAcctsManage.py
bin/marmeMsgLib.py
bin/marmeRuns.py
bin/marmeSendExample.py
bin/marmeSendIcm.py
bin/marmeTrackingIcm.py
bin/pkgMarmeManage.py
unisos2/__init__.py
unisos2.marme.egg-info/PKG-INFO
unisos2.marme.egg-info/SOURCES.txt
unisos2.marme.egg-info/dependency_links.txt
unisos2.marme.egg-info/namespace_packages.txt
unisos2.marme.egg-info/not-zip-safe
unisos2.marme.egg-info/requires.txt
unisos2.marme.egg-info/top_level.txt
unisos2/marme/__init__.py
unisos2/marme/marmeAcctsLib.py
unisos2/marme/marmePkgThis.py
unisos2/marme/marmeSendLib.py
unisos2/marme/marmeTrackingLib.py